jupysec/__init__.py
jupysec/finding.py
jupysec/rules.py
jupysec-0.1.17.dist-info/LICENSE
jupysec-0.1.17.dist-info/METADATA
jupysec-0.1.17.dist-info/WHEEL
jupysec-0.1.17.dist-info/top_level.txt
jupysec-0.1.17.dist-info/RECORD
