Metadata-Version: 2.1
Name: jupysec
Version: 0.1.17
Summary: Jupyter Security Utilities
Author-email: Joe Lucas <joe@joetl.com>
Project-URL: Homepage, https://github.com/JosephTLucas/jupysec
Project-URL: Bug Tracker, https://github.com/JosephTLucas/jupysec/issues
Classifier: Programming Language :: Python :: 3
Classifier: License :: OSI Approved :: MIT License
Classifier: Operating System :: OS Independent
Requires-Python: >=3.7
License-File: LICENSE
Provides-Extra: jupyterlab
Requires-Dist: jupysec-extension ; extra == 'jupyterlab'
